javajar/__init__.py
javajar/__main__.py
javajar/app_version.py
javajar/cli.py
javajar/java_list.py
javajar/java_runner.py
javajar/jdk_manager.py
javajar/maven_resolver.py
javajar/os_util.py
javajar-0.3.3.dist-info/METADATA
javajar-0.3.3.dist-info/WHEEL
javajar-0.3.3.dist-info/entry_points.txt
javajar-0.3.3.dist-info/licenses/LICENSE
javajar-0.3.3.dist-info/RECORD
