Metadata-Version: 2.4
Name: javajar
Version: 0.3.3
Summary: 通过python运行java，会自动下载java运行环境
Author-email: yanglikun <yanglikun@gmail.com>
License-Expression: MIT
License-File: LICENSE
Requires-Python: >=3.10
Requires-Dist: loguru>=0.7.3
Requires-Dist: requests>=2.32.5
Requires-Dist: typer>=0.20.0
Provides-Extra: test
Requires-Dist: pytest>=7.0; extra == 'test'
